<skills>
	<skill1>Base Qa theory</skill1>
	<skill2>Client-server architecture</skill2>
	<skill3>HTTP</skill3>
	<skill4>JSON, XML</skill4>
	<skill5>API testing</skill5>
	<skill6>Log processing</skill6>
	<skill7>Traffic sniffing</skill7>
	<skill8>Dev Tools</skill8>
	<skill9>VPN</skill9>
	<skill10>Mobile testing</skill10>
	<skill11>iOS, Android features</skill11>
	<skill12>Bash</skill12>
	<skill13>SQL</skill13>
	<skill14>Scrum</skill14>
	<skill15>Python</skill15>
	<skill16>Stress testing</skill16>
</skills>
